auto_timelapse.py
cmpc_timelapse-0.9.6.dist-info/LICENSE
cmpc_timelapse-0.9.6.dist-info/METADATA
cmpc_timelapse-0.9.6.dist-info/WHEEL
cmpc_timelapse-0.9.6.dist-info/entry_points.txt
cmpc_timelapse-0.9.6.dist-info/top_level.txt
cmpc_timelapse-0.9.6.dist-info/RECORD
