Metadata-Version: 2.1
Name: cmpc-timelapse
Version: 0.9.6
Summary: Script for automatically downloading a list of videos, speeding them up, and concatenating them.
Home-page: https://github.com/JMcB17/auto_timelapse_script
Author: Joel McBride
Author-email: joel.mcbride1@live.com
License: GPLv3
Platform: UNKNOWN
Classifier: Programming Language :: Python :: 3
Classifier: License :: OSI Approved :: GNU General Public License v3 (GPLv3)
Classifier: Development Status :: 3 - Alpha
Classifier: Environment :: Console
Requires-Python: >=3
Requires-Dist: ffmpeg-python
Requires-Dist: youtube-dl
